{
  "languageModel": {
    "types": [
      {
        "name": "prayerNames",
        "values": [
          {
            "id": null,
            "name": {
              "value": "our father",
              "synonyms": []
            }
          },
          {
            "id": null,
            "name": {
              "value": "glory be",
              "synonyms": []
            }
          },
          {
            "id": null,
            "name": {
              "value": "the apostles creed",
              "synonyms": []
            }
          },
          {
            "id": null,
            "name": {
              "value": "hail holy queen",
              "synonyms": []
            }
          },
          {
            "id": null,
            "name": {
              "value": "anima christi",
              "synonyms": []
            }
          },
          {
            "id": null,
            "name": {
              "value": "memorare",
              "synonyms": []
            }
          },
          {
            "id": null,
            "name": {
              "value": "the angelus",
              "synonyms": []
            }
          },
          {
            "id": null,
            "name": {
              "value": "saint michael prayer",
              "synonyms": []
            }
          },
          {
            "id": null,
            "name": {
              "value": "act of contrition",
              "synonyms": []
            }
          },
          {
            "id": null,
            "name": {
              "value": "miraculous medal prayer",
              "synonyms": []
            }
          },
          {
            "id": null,
            "name": {
              "value": "morning offering",
              "synonyms": []
            }
          },
          {
            "id": null,
            "name": {
              "value": "guardian angel prayer",
              "synonyms": []
            }
          },
          {
            "id": null,
            "name": {
              "value": "grace before meals",
              "synonyms": []
            }
          },
          {
            "id": null,
            "name": {
              "value": "grace after meals",
              "synonyms": []
            }
          },
          {
            "id": null,
            "name": {
              "value": "anima Kristy",
              "synonyms": []
            }
          },
          {
            "id": null,
            "name": {
              "value": "hail Mary",
              "synonyms": []
            }
          },
          {
            "id": null,
            "name": {
              "value": "the nicene creed",
              "synonyms": []
            }
          },
          {
            "id": null,
            "name": {
              "value": "pray to saint Joseph",
              "synonyms": []
            }
          },
          {
            "id": null,
            "name": {
              "value": "pray to the holy spirit",
              "synonyms": []
            }
          },
          {
            "id": null,
            "name": {
              "value": "serenity prayer",
              "synonyms": []
            }
          },
          {
            "id": null,
            "name": {
              "value": "salve regina",
              "synonyms": []
            }
          },
          {
            "id": null,
            "name": {
              "value": "act of faith",
              "synonyms": []
            }
          },
          {
            "id": null,
            "name": {
              "value": "act of hope",
              "synonyms": []
            }
          },
          {
            "id": null,
            "name": {
              "value": "act of love",
              "synonyms": []
            }
          },
          {
            "id": null,
            "name": {
              "value": "litany of the blessed virgin Mary",
              "synonyms": []
            }
          },
          {
            "id": null,
            "name": {
              "value": "prayer before meals",
              "synonyms": []
            }
          },
          {
            "id": null,
            "name": {
              "value": "prayer after meals",
              "synonyms": []
            }
          }
        ]
      }
    ],
    "intents": [
      {
        "name": "AMAZON.CancelIntent",
        "samples": [
          "no",
          "cancel",
          "stop",
          "no thank you",
          "no thanks"
        ]
      },
      {
        "name": "AMAZON.HelpIntent",
        "samples": [
          "help"
        ]
      },
      {
        "name": "AMAZON.StopIntent",
        "samples": [
          "stop",
          "cancel",
          "no",
          "no thanks",
          "no thank you"
        ]
      },
      {
        "name": "PickPrayerIntent",
        "samples": [
          "pick a prayer"
        ],
        "slots": []
      },
      {
        "name": "PrayersIntent",
        "samples": [
          "{prayer}",
          "Say {prayer}",
          "Say the {prayer}",
          "Say {prayer} prayer",
          "Say the {prayer} prayer",
          "Please say the {prayer}",
          "Please say the {prayer} prayer",
          "to do {prayer}"
        ],
        "slots": [
          {
            "name": "prayer",
            "type": "prayerNames"
          }
        ]
      },
      {
        "name": "YesIntent",
        "samples": [
          "yes",
          "yeah",
          "yes please",
          "please"
        ],
        "slots": []
      }
    ],
    "invocationName": "catholic prayers"
  }
}